bitrixUtils/__init__.py
bitrixUtils/core.py
bitrixUtils/utils.py
tests/__init__.py
tests/deployAcessorias.py
tests/deploySittax.py
tests/test_core.py
tests/test_core_card.py
tests/test_lead.py
bitrixUtils-0.1.8.dist-info/METADATA
bitrixUtils-0.1.8.dist-info/WHEEL
bitrixUtils-0.1.8.dist-info/top_level.txt
bitrixUtils-0.1.8.dist-info/RECORD
