Metadata-Version: 2.2
Name: bitrixUtils
Version: 0.1.8
Summary: Uma biblioteca para facilitar a integração com a API do Bitrix24
Home-page: https://github.com/RafaelZelak/bitrixUtils.git
Author: Rafael Zelak Fernandes
Author-email: rzf1503@gmail.com
Classifier: Programming Language :: Python :: 3
Classifier: License :: OSI Approved :: MIT License
Classifier: Operating System :: OS Independent
Requires-Python: >=3.6
Requires-Dist: requests
Dynamic: author
Dynamic: author-email
Dynamic: classifier
Dynamic: description
Dynamic: description-content-type
Dynamic: home-page
Dynamic: requires-dist
Dynamic: requires-python
Dynamic: summary
